bukmacherska_crystal/__init__.py
bukmacherska_crystal/bukmacherska_crystal.py
bukmacherska_crystal-0.1.0.dist-info/LICENSE
bukmacherska_crystal-0.1.0.dist-info/METADATA
bukmacherska_crystal-0.1.0.dist-info/WHEEL
bukmacherska_crystal-0.1.0.dist-info/top_level.txt
bukmacherska_crystal-0.1.0.dist-info/RECORD
