Metadata-Version: 2.2
Name: bukmacherska_crystal
Version: 0.1.0
Summary: Biblioteka do przewidywania wyników różnych zdarzeń w meczach piłkarskich
Home-page: https://github.com/twoj_repo/bukmacherska_crystal
Author: Twoje Imię
Author-email: twojemail@example.com
Classifier: Programming Language :: Python :: 3
Classifier: License :: OSI Approved :: MIT License
Classifier: Operating System :: OS Independent
Requires-Python: >=3.6
License-File: LICENSE
Requires-Dist: numpy
Requires-Dist: scipy
Requires-Dist: matplotlib
Requires-Dist: scikit-learn
Requires-Dist: pandas
Requires-Dist: lightgbm
Requires-Dist: bukmacherska
Dynamic: author
Dynamic: author-email
Dynamic: classifier
Dynamic: description
Dynamic: description-content-type
Dynamic: home-page
Dynamic: requires-dist
Dynamic: requires-python
Dynamic: summary
